opendbm/__init__.py
opendbm/api_lib/__init__.py
opendbm/api_lib/_derive.py
opendbm/api_lib/model.py
opendbm/api_lib/util.py
opendbm/api_lib/facial_activity/__init__.py
opendbm/api_lib/facial_activity/_action_unit.py
opendbm/api_lib/facial_activity/_asymmetry.py
opendbm/api_lib/facial_activity/_expressivity.py
opendbm/api_lib/facial_activity/_landmark.py
opendbm/api_lib/facial_activity/api.py
opendbm/api_lib/movement/__init__.py
opendbm/api_lib/movement/_eye_blink.py
opendbm/api_lib/movement/_eye_gaze.py
opendbm/api_lib/movement/_facial_tremor.py
opendbm/api_lib/movement/_head_movement.py
opendbm/api_lib/movement/_vocal_tremor.py
opendbm/api_lib/movement/api.py
opendbm/api_lib/speech/__init__.py
opendbm/api_lib/speech/_speech_features.py
opendbm/api_lib/speech/_transcribe.py
opendbm/api_lib/speech/api.py
opendbm/api_lib/verbal_accoustics/__init__.py
opendbm/api_lib/verbal_accoustics/_audio_intensity.py
opendbm/api_lib/verbal_accoustics/_formant_frequency.py
opendbm/api_lib/verbal_accoustics/_glottal_noise.py
opendbm/api_lib/verbal_accoustics/_harmonic_noise.py
opendbm/api_lib/verbal_accoustics/_jitter.py
opendbm/api_lib/verbal_accoustics/_mfcc.py
opendbm/api_lib/verbal_accoustics/_pause_characteristics.py
opendbm/api_lib/verbal_accoustics/_pitch_frequency.py
opendbm/api_lib/verbal_accoustics/_shimmer.py
opendbm/api_lib/verbal_accoustics/_voice_prevalence.py
opendbm/api_lib/verbal_accoustics/api.py
opendbm/dbm_lib/__init__.py
opendbm/dbm_lib/config/__init__.py
opendbm/dbm_lib/config/config_derive_feature.py
opendbm/dbm_lib/config/config_raw_feature.py
opendbm/dbm_lib/config/config_reader.py
opendbm/dbm_lib/controller/__init__.py
opendbm/dbm_lib/controller/process_feature.py
opendbm/dbm_lib/dbm_features/__init__.py
opendbm/dbm_lib/dbm_features/derived_features/__init__.py
opendbm/dbm_lib/dbm_features/derived_features/derive.py
opendbm/dbm_lib/dbm_features/raw_features/__init__.py
opendbm/dbm_lib/dbm_features/raw_features/audio/__init__.py
dbm_test123-0.1.17.dist-info/LICENSE
dbm_test123-0.1.17.dist-info/METADATA
dbm_test123-0.1.17.dist-info/WHEEL
dbm_test123-0.1.17.dist-info/top_level.txt
dbm_test123-0.1.17.dist-info/RECORD
